{
    "backend": "flask",
    "db_name": "",
    "db_pass": "",
    "db_type": "sqlite",
    "db_user": "",
    "dbms": "1",
    "description": "generated product",
    "design": "datta-able",
    "docker": "1",
    "err_code": 0,
    "frontend": "",
    "heroku": "0",
    "pattern": "mvc",
    "pro": "0",
    "task_id": "b646e690-f782-4f33-a6cb-e003edb479e9",
    "task_info": "Upload Sources [0%] - 148 files",
    "task_output": "b646e690-f782-4f33-a6cb-e003edb479e9.zip",
    "task_result": "SUCCESS",
    "task_state": "RUNNING",
    "task_ts_end": "2025-02-23-07-52-35",
    "task_ts_start": "2025-02-23-07-52-34"
}